[{"id":5637,"title":"AD4343","q":"3","t":{"label":{"value":"Assembly","label":"Assembly"},"value":{"value":"Assembly","label":"Assembly"}},"tc":false,"i":"assembly"},{"id":5638,"title":"AD4343 XT","q":"6","t":{"label":{"value":"Assembly","label":"Assembly"},"value":{"value":"Assembly","label":"Assembly"}},"tc":false,"i":"assembly"},{"id":5632,"title":"P0383","q":"5","t":{"label":{"value":"Part","label":"Part"},"value":{"value":"Part","label":"Part"}},"tc":false,"i":"part"},{"id":5640,"title":"S5454 XT","q":"1.0","t":{"label":{"value":"Assembly","label":"Assembly"},"value":{"value":"Assembly","label":"Assembly"}},"tc":false,"i":"assembly"}]